CHANGELOG
COPYING
LICENSE
MANIFEST.in
README.md
README.txt
setup.py
uclassify/__init__.py
uclassify/uclassify.py
uclassify/uclassify_eh.py
uclassify/uclassify_endpoints.py
uclassify.egg-info/PKG-INFO
uclassify.egg-info/SOURCES.txt
uclassify.egg-info/dependency_links.txt
uclassify.egg-info/requires.txt
uclassify.egg-info/top_level.txt