Metadata-Version: 1.1
Name: uclassify
Version: 0.1.2
Summary: Python Wrapper for accessing uClassify services
Home-page: https://github.com/psibi/pyuClassify
Author: Sibi
Author-email: sibi@psibi.in
License: GNU GPLv3
Keywords: uClassify API
Platform: UNKNOWN
Classifier: Development Status :: 4 - Beta
Classifier: Intended Audience :: Developers
Classifier: License :: OSI Approved :: GNU General Public License v3 (GPLv3)
Classifier: Topic :: Software Development :: Libraries :: Python Modules
Classifier: Topic :: Internet
